pixabay/__init__.py
pixabay.py_OBLIQUEE-0.0.1.dist-info/LICENSE
pixabay.py_OBLIQUEE-0.0.1.dist-info/METADATA
pixabay.py_OBLIQUEE-0.0.1.dist-info/WHEEL
pixabay.py_OBLIQUEE-0.0.1.dist-info/top_level.txt
pixabay.py_OBLIQUEE-0.0.1.dist-info/RECORD
